sagui_client/__init__.py
sagui_client/sagui_client.py
sagui_client-0.0.5.dist-info/licenses/LICENSE
sagui_client-0.0.5.dist-info/METADATA
sagui_client-0.0.5.dist-info/WHEEL
sagui_client-0.0.5.dist-info/top_level.txt
sagui_client-0.0.5.dist-info/RECORD
