Metadata-Version: 2.4
Name: sagui_client
Version: 0.0.5
Summary: An exception handler that sends error info to Sagui, the opensource AI-powered error analysis tool
Author-email: Jorge Junior Arteaga Carvalho <jorgearteaga8936@gmail.com>
License-Expression: MIT
Classifier: Programming Language :: Python :: 3
Classifier: Operating System :: OS Independent
Requires-Python: >=3.8
License-File: LICENSE
Requires-Dist: requests>=2.25.0
Dynamic: license-file
